[
	["id","taskId","type","taskName","taskBeginTime","taskEndTime","taskExpireTime","minLevel","maxLevel","needSociaty","sociatyValue","questNpcId","completeNpcId","taskProp","taskGoal","taskDescription","taskTalkNum","taskTalk","notCompleteText","completeText","getExp","getMoney","rewardName","rewardItems","isBroadcast","nextTaskId","showNpcId","hideNpcId","_id"],
	["id","taskId","type","taskName","taskBeginTime","taskEndTime","taskExpireTime","minLevel","maxLevel","needSociaty","sociatyValue","questNpcId","completeNpcId","taskProp","taskGoal","taskDescription","taskTalkNum","taskTalk","notCompleteText","completeText","getExp","getMoney","rewardName","rewardItems","isBroadcast","nextTaskId","showNpcId","hideNpcId","_id"],
	[10101,10101,1,"杀杀怪",0,0,0,0,0,0,0,10101,10101,"",{"type":1,"itemId":1,"itemNum":10},"杀杀怪",2,{"talks":[{"npcId":10101,"npc":"做个任务呗","player":"啥啊"},{"npcId":10102,"npc":"杀杀怪","player":"好嘞~"}]},"还在磨刀啊，快去杀啊！","很迅速嘛~",50,50,"","",0,10002,10102,10101,1],
	[10102,10102,1,"收集物品",0,0,0,0,0,0,0,10102,10102,"",{"type":1,"itemId":1,"itemNum":10},"收集物品",2,{"talks":[{"npcId":10102,"npc":"来找我了？","player":"恩"},{"npcId":10101,"npc":"小狗身上掉雪糕，弄几个去呗~","player":"正好我也想吃"}]},"好热的天啊，要有雪糕吃就好了","这么多啊，我吃个可爱多就好了。",50,50,"可爱多","",1,10003,10101,10102,2],
	[10201,10201,1,"打打副本",0,0,0,0,0,0,0,10201,10201,"",{"type":1,"itemId":1,"itemNum":10},"打副本",2,{"talks":[{"npcId":10201,"npc":"来第二个城市了啊？","player":"其他地能去也行啊"},{"npcId":10201,"npc":"有个副本等着你打呢。","player":"我就知道闲不着"}]},"通关有奖励哦~","主线任务没了",50,50,"","",0,0,0,0,3],
	[20201,20201,2,"穿装备",0,0,0,0,0,0,0,10201,10201,"",{"type":1,"itemId":1,"itemNum":10},"穿上装备",1,{"talks":[{"npcId":10201,"npc":"穿上这个装备吧","player":"终于不裸了"}]},"穿了没？","下一个~",30,30,"","",0,20202,0,0,4],
	[20202,20202,2,"升级",0,0,0,0,0,0,0,10201,10201,"",{"type":1,"itemId":1,"itemNum":10},"升到5级",3,{"talks":[{"npcId":10201,"npc":"现在几级了？","player":"你不会看啊"},{"npcId":10201,"npc":"懒得看","player":"懒得说"},{"npcId":10201,"npc":"拿到你五级的时候来找我吧","player":"好"}]},"嗯哼？","其实我也没啥事。",50,50,"","",0,0,0,0,5],
	[30201,30201,3,"升级装备",0,0,0,0,10,0,0,10202,10202,"",{"type":1,"itemId":1,"itemNum":10},"升级一次装备",1,{"talks":[{"npcId":10202,"npc":"升级一下装备呗","player":"行啊"}]},"很简单的，速去速回。","很厉害呀",50,50,"","",0,30202,0,0,6],
	[30202,30202,3,"排兵布阵",0,0,0,10,0,1,0,10202,10202,"",{"type":1,"itemId":1,"itemNum":10},"更换一次阵型",2,{"talks":[{"npcId":10202,"npc":"阵型有点乱啊，","player":"还好"},{"npcId":10202,"npc":"能换个不？","player":"能"}]},"那就换呗","这回顺眼了",50,50,"","",0,30203,0,0,7],
	[30203,30203,3,"真金白银",0,0,0,0,0,0,0,10202,10202,"",{"type":1,"itemId":1,"itemNum":10},"花费十个元宝",2,{"talks":[{"npcId":10202,"npc":"要养成乱花钱的好习惯","player":"恩"},{"npcId":10202,"npc":"那去花十个吧","player":"。。。"}]},"养成习惯嘛~","又乱花钱，这可是日常啊！",50,50,"","",0,0,0,0,8],
	[40201,40201,4,"打酱油",13,15,0,0,0,0,0,10203,10203,"",{"type":1,"itemId":1,"itemNum":10},"通关节日副本",1,{"talks":[{"npcId":10203,"npc":"过节了，有个节日BOSS，去吧","player":"去就去"}]},"节日boss很给力的。","奖励很多吧~",50,50,"","",0,0,0,0,9],
	[40202,40202,4,"节日小奢侈",13,20,20,0,0,0,0,10203,10203,"",{"type":1,"itemId":1,"itemNum":10},"过节了，奢侈一把",2,{"talks":[{"npcId":10203,"npc":"过节了奢侈一把呗~","player":"站着说话不腰疼"},{"npcId":10203,"npc":"去吧，回来我报销","player":"早说~"}]},"有发票才给报销呢","有发票才给报销呢",50,50,"","",0,0,0,0,10]
]